parity_gen.v
`timescale 1ns / 1ps

module parity_gen (
    input  wire [9:0] data_in,
    output wire       parity
);

    assign parity = ^data_in;  // XOR reduction = parity bit

endmodule

lfsr.v
`timescale 1ns / 1ps

module lfsr #(parameter WIDTH = 10)(
    input  wire clk,
    input  wire rst,
    output reg [WIDTH-1:0] rnd
);

    always @(posedge clk or posedge rst) begin
        if (rst) begin
            rnd <= {WIDTH{1'b1}}; // seed: all 1s
        end else begin
            // Example taps for 10-bit LFSR: bits 9 and 6
            rnd <= {rnd[WIDTH-2:0], rnd[WIDTH-1] ^ rnd[6]};
        end
    end

endmodule

barrel_shifter.v
`timescale 1ns / 1ps

module barrel_shifter (
    input  wire [9:0] data_in,     // 10-bit input
    input  wire [2:0] shift_amt,   // shift amount (0–7)
    output reg  [9:0] data_out     // shifted result
);

    always @(*) begin
        case (shift_amt)
            3'd0: data_out = data_in;
            3'd1: data_out = data_in << 1;
            3'd2: data_out = data_in << 2;
            3'd3: data_out = data_in << 3;
            3'd4: data_out = data_in << 4;
            3'd5: data_out = data_in << 5;
            3'd6: data_out = data_in << 6;
            3'd7: data_out = data_in >> 1; // just for variety, shift right
            default: data_out = data_in;
        endcase
    end

endmodule

clk_divider.v
// clk_divider.v
module clk_divider #(parameter div_value = 10)(
    input  wire clk_in,
    input  wire rst,
    output reg  clk_out = 1'b0
);
    reg [3:0] count = 4'd0;
    always @(posedge clk_in or posedge rst) begin
        if (rst) begin
            // This logic is active on the RISING EDGE of reset.
            count   <= 4'd0;
            clk_out <= 1'b0;
        end else begin
            // This logic is active on the RISING EDGE of the clock.
            if (count == div_value - 1) begin
                count   <= 4'd0;
                clk_out <= ~clk_out;
            end else begin
                count <= count + 1;
            end
        end
    end
endmodule

rtl_topmodule.v
`timescale 1ns / 1ps
module rtl_topmodule (
    input  wire        clk,
    input  wire        rst,
    input  wire [9:0]  A,
    input  wire [8:0]  C,
    output reg  [10:0] out
);
    reg [9:0]  A_reg;
    reg [8:0]  C_reg;
    reg [10:0] out_reg;
    always @(posedge clk) begin
        if (rst) begin
            A_reg <= 10'd0;
            C_reg <= 9'd0;
        end else begin
            A_reg <= A;
            C_reg <= C;
        end
    end

    wire clk_div;
    clk_divider #(.div_value(4)) u1 (
        .clk_in (clk),
        .clk_out(clk_div)
    );

    wire [9:0] shifter_out;
    barrel_shifter u2 (
        .data_in (A_reg),
        .shift_amt(C_reg[2:0]),
        .data_out(shifter_out)
    );

    wire [9:0] lfsr_out;
    lfsr #(.WIDTH(10)) u3 (
        .clk(clk),
        .rst(rst),
        .rnd(lfsr_out)
    );

    wire parity_out;
    parity_gen u4 (
        .data_in(A_reg),
        .parity (parity_out)
    );

    always @(*) begin
        if (C_reg < 9'd51) begin
            out_reg = {10'd0, clk_div};
        end else if (C_reg < 9'd100) begin
            out_reg = {1'd0, shifter_out};
        end else if (C_reg <= 9'd128) begin
            out_reg = {10'd0, parity_out};
        end else begin
            out_reg = {1'd0, lfsr_out};
        end
    end

    always @(posedge clk) begin
        if (rst) out <= 11'd0;
        else     out <= out_reg;
    end
endmodule

testbench_parity_rtl.v
`timescale 1ns/1ns

module testbench_parity_rtl;

    // Signals for the top module
    reg clk;
    reg rst;
    reg [9:0] A;
    reg [8:0] C;
    wire [10:0] out;

    // Instantiate the full rtl_topmodule
    rtl_topmodule dut (
        .clk(clk),
        .rst(rst),
        .A(A),
        .C(C),
        .out(out)
    );

    // Clock generation (10ns period)
    initial begin
        clk = 1'b0;
        forever #5 clk = ~clk;
    end

    // Waveform setup
    initial begin
        $dumpfile("testbench_parity_rtl.vcd");
        $dumpvars(0, testbench_parity_rtl);
    end

    // --- Main Stimulus ---
    initial begin
        $display("Starting Parity Generator Integration Test...");
        
        // 1. Correct Reset Pulse
        rst = 0; A = 0; C = 0;
        #20; rst = 1; #20; rst = 0;

        // 2. Set C to 110 (this is in the range 100 to 128)
        // This tells the "brain" to select the Parity Generator
        C = 9'd110; 
        #10; 

        // 3. Test Case A: Input with ODD number of 1s
        // Binary: 00 0000 0001 (One '1') -> Parity should be 1
        A = 10'b0000000001; 
        #20; // Wait for clock edge to register the output

        // 4. Test Case B: Input with EVEN number of 1s
        // Binary: 00 0000 0011 (Two '1's) -> Parity should be 0
        A = 10'b0000000011; 
        #20;

        // 5. Test Case C: All 1s
        // Binary: 11 1111 1111 (Ten '1's - Even) -> Parity should be 0
        A = 10'b1111111111; 
        #20;

        // 6. Test Case D: Nine 1s
        // Binary: 11 1111 1110 (Nine '1's - Odd) -> Parity should be 1
        A = 10'b1111111110; 
        #20;

        $display("Test Finished.");
        $finish;
    end

    // Monitor for console output
    initial begin
        $monitor("Time=%0t | C=%d | A=%b | out[0] (Parity)=%b", 
                 $time, C, A, out[0]);
    end

endmodule

testbench_parity_rtl.vcd
$date
	Wed Dec 17 20:35:30 2025
$end
$version
	Icarus Verilog
$end
$timescale
	1ps
$end
$scope module testbench_parity_rtl $end
$var wire 11 ! out [10:0] $end
$var reg 10 " A [9:0] $end
$var reg 9 # C [8:0] $end
$var reg 1 $ clk $end
$var reg 1 % rst $end
$scope module dut $end
$var wire 10 & A [9:0] $end
$var wire 9 ' C [8:0] $end
$var wire 1 $ clk $end
$var wire 1 % rst $end
$var wire 10 ( shifter_out [9:0] $end
$var wire 1 ) parity_out $end
$var wire 10 * lfsr_out [9:0] $end
$var wire 1 + clk_div $end
$var reg 10 , A_reg [9:0] $end
$var reg 9 - C_reg [8:0] $end
$var reg 11 . out [10:0] $end
$var reg 11 / out_reg [10:0] $end
$scope module u1 $end
$var wire 1 $ clk_in $end
$var wire 1 0 rst $end
$var parameter 32 1 div_value $end
$var reg 1 + clk_out $end
$var reg 4 2 count [3:0] $end
$upscope $end
$scope module u2 $end
$var wire 10 3 data_in [9:0] $end
$var wire 3 4 shift_amt [2:0] $end
$var reg 10 5 data_out [9:0] $end
$upscope $end
$scope module u3 $end
$var wire 1 $ clk $end
$var wire 1 % rst $end
$var parameter 32 6 WIDTH $end
$var reg 10 7 rnd [9:0] $end
$upscope $end
$scope module u4 $end
$var wire 10 8 data_in [9:0] $end
$var wire 1 ) parity $end
$upscope $end
$upscope $end
$upscope $end
$enddefinitions $end
$dumpall
b1010 6
b100 1
$end
#0
$dumpvars
bx 8
bx 7
bx 5
bx 4
bx 3
b0 2
z0
b0xxxxxxxxxx /
bx .
bx -
bx ,
0+
bx *
x)
bx (
b0 '
b0 &
0%
0$
b0 #
b0 "
bx !
$end
#5000
b0 4
b0 (
b0 5
b0 /
b1 2
b0 -
0)
b0 ,
b0 3
b0 8
b0xxxxxxxxxx !
b0xxxxxxxxxx .
1$
#10000
0$
#15000
b10 2
b0 !
b0 .
1$
#20000
b1111111111 *
b1111111111 7
0$
1%
#25000
b11 2
1$
#30000
0$
#35000
b1 /
1+
b0 2
1$
#40000
0$
b1101110 #
b1101110 '
0%
#45000
b0 /
b110 4
b1 2
b1111111110 *
b1111111110 7
b1101110 -
b1 !
b1 .
1$
#50000
0$
b1 "
b1 &
#55000
b1000000 (
b1000000 5
b1 /
b10 2
b1111111100 *
b1111111100 7
b0 !
b0 .
1)
b1 ,
b1 3
b1 8
1$
#60000
0$
#65000
b11 2
b1111111000 *
b1111111000 7
b1 !
b1 .
1$
#70000
0$
b11 "
b11 &
#75000
b11000000 (
b11000000 5
b0 /
0+
b0 2
b1111110000 *
b1111110000 7
0)
b11 ,
b11 3
b11 8
1$
#80000
0$
#85000
b1 2
b1111100000 *
b1111100000 7
b0 !
b0 .
1$
#90000
0$
b1111111111 "
b1111111111 &
#95000
b1111000000 (
b1111000000 5
b10 2
b1111000000 *
b1111000000 7
b1111111111 ,
b1111111111 3
b1111111111 8
1$
#100000
0$
#105000
b11 2
b1110000000 *
b1110000000 7
1$
#110000
0$
b1111111110 "
b1111111110 &
#115000
b1110000000 (
b1110000000 5
b1 /
1+
b0 2
b1100000001 *
b1100000001 7
1)
b1111111110 ,
b1111111110 3
b1111111110 8
1$
#120000
0$
#125000
b1 2
b1000000011 *
b1000000011 7
b1 !
b1 .
1$
