parity_gen.v
`timescale 1ns / 1ps

module parity_gen (
    input  wire [9:0] data_in,
    output wire       parity
);

    assign parity = ^data_in;  // XOR reduction = parity bit

endmodule

lfsr.v
`timescale 1ns / 1ps

module lfsr #(parameter WIDTH = 10)(
    input  wire clk,
    input  wire rst,
    output reg [WIDTH-1:0] rnd
);

    always @(posedge clk or posedge rst) begin
        if (rst) begin
            rnd <= {WIDTH{1'b1}}; // seed: all 1s
        end else begin
            // Example taps for 10-bit LFSR: bits 9 and 6
            rnd <= {rnd[WIDTH-2:0], rnd[WIDTH-1] ^ rnd[6]};
        end
    end

endmodule

barrel_shifter.v
`timescale 1ns / 1ps

module barrel_shifter (
    input  wire [9:0] data_in,     // 10-bit input
    input  wire [2:0] shift_amt,   // shift amount (0–7)
    output reg  [9:0] data_out     // shifted result
);

    always @(*) begin
        case (shift_amt)
            3'd0: data_out = data_in;
            3'd1: data_out = data_in << 1;
            3'd2: data_out = data_in << 2;
            3'd3: data_out = data_in << 3;
            3'd4: data_out = data_in << 4;
            3'd5: data_out = data_in << 5;
            3'd6: data_out = data_in << 6;
            3'd7: data_out = data_in >> 1; // just for variety, shift right
            default: data_out = data_in;
        endcase
    end

endmodule

clk_divider.v
// clk_divider.v
module clk_divider #(parameter div_value = 10)(
    input  wire clk_in,
    input  wire rst,
    output reg  clk_out = 1'b0
);
    reg [3:0] count = 4'd0;
    always @(posedge clk_in or posedge rst) begin
        if (rst) begin
            // This logic is active on the RISING EDGE of reset.
            count   <= 4'd0;
            clk_out <= 1'b0;
        end else begin
            // This logic is active on the RISING EDGE of the clock.
            if (count == div_value - 1) begin
                count   <= 4'd0;
                clk_out <= ~clk_out;
            end else begin
                count <= count + 1;
            end
        end
    end
endmodule

rtl_topmodule.v
`timescale 1ns / 1ps
module rtl_topmodule (
    input  wire        clk,
    input  wire        rst,
    input  wire [9:0]  A,
    input  wire [8:0]  C,
    output reg  [10:0] out
);
    reg [9:0]  A_reg;
    reg [8:0]  C_reg;
    reg [10:0] out_reg;
    always @(posedge clk) begin
        if (rst) begin
            A_reg <= 10'd0;
            C_reg <= 9'd0;
        end else begin
            A_reg <= A;
            C_reg <= C;
        end
    end

    wire clk_div;
    clk_divider #(.div_value(4)) u1 (
        .clk_in (clk),
        .clk_out(clk_div)
    );

    wire [9:0] shifter_out;
    barrel_shifter u2 (
        .data_in (A_reg),
        .shift_amt(C_reg[2:0]),
        .data_out(shifter_out)
    );

    wire [9:0] lfsr_out;
    lfsr #(.WIDTH(10)) u3 (
        .clk(clk),
        .rst(rst),
        .rnd(lfsr_out)
    );

    wire parity_out;
    parity_gen u4 (
        .data_in(A_reg),
        .parity (parity_out)
    );

    always @(*) begin
        if (C_reg < 9'd51) begin
            out_reg = {10'd0, clk_div};
        end else if (C_reg < 9'd100) begin
            out_reg = {1'd0, shifter_out};
        end else if (C_reg <= 9'd128) begin
            out_reg = {10'd0, parity_out};
        end else begin
            out_reg = {1'd0, lfsr_out};
        end
    end

    always @(posedge clk) begin
        if (rst) out <= 11'd0;
        else     out <= out_reg;
    end
endmodule

testbench_clk_rtl.v
`timescale 1ns/1ns

module testbench_clk_rtl;

    // Declare signals
    reg clk;
    reg rst;
    reg [9:0] A;
    reg [8:0] C;
    wire [10:0] out;

    // Instantiate the DUT (Device Under Test)
    rtl_topmodule dut (
        .clk(clk),
        .rst(rst),
        .A(A),
        .C(C),
        .out(out)
    );

    // Clock generation
    initial begin
        clk = 1'b0;
        forever #5 clk = ~clk;
    end

    // ==========================================================
    // --- Stimulus process with THE CORRECTED RESET SEQUENCE ---
    // ==========================================================
    initial begin
        $display($time, " ===== Testbench Start ===== ");
        
        // 1. Start with reset LOW to allow for a rising edge.
        rst = 0;
        A   = 10'd15;
        C   = 9'd0;
        #20; // Wait for 2 clock cycles to ensure simulation is stable.

        // 2. Apply the reset pulse (0 -> 1 -> 0). This will correctly initialize the counter.
        rst = 1;
        #20; // Hold reset high for 20ns.
        rst = 0; // De-assert reset to begin normal operation.

        // 3. Now, apply the stimulus to test the clock divider.
        #10; // Wait a moment after reset.
        C = 9'd12; // This will trigger the clk_divider because C < 51.
    end

    // VCD dump for waveform and coverage
    initial begin
        $dumpfile("testbench_clk_rtl.vcd");
        $dumpvars(0, testbench_clk_rtl);  // Dump all hierarchy below testbench_1
    end

    // Monitor output (Output would be shown on the terminal)
    initial begin
        $monitor("Time=%0t | clk=%b rst=%b | A=%d C=%d | out=%d",
                 $time, clk, rst, A, C, out);
    end

    // Terminate simulation after a fixed time
    initial begin
        #500 $finish;
    end

endmodule

testbench_clk_rtl.vcd
$date
	Wed Dec 17 18:55:32 2025
$end
$version
	Icarus Verilog
$end
$timescale
	1ps
$end
$scope module testbench_clk_rtl $end
$var wire 11 ! out [10:0] $end
$var reg 10 " A [9:0] $end
$var reg 9 # C [8:0] $end
$var reg 1 $ clk $end
$var reg 1 % rst $end
$scope module dut $end
$var wire 10 & A [9:0] $end
$var wire 9 ' C [8:0] $end
$var wire 1 $ clk $end
$var wire 1 % rst $end
$var wire 10 ( shifter_out [9:0] $end
$var wire 1 ) parity_out $end
$var wire 10 * lfsr_out [9:0] $end
$var wire 1 + clk_div $end
$var reg 10 , A_reg [9:0] $end
$var reg 9 - C_reg [8:0] $end
$var reg 11 . out [10:0] $end
$var reg 11 / out_reg [10:0] $end
$scope module u1 $end
$var wire 1 $ clk_in $end
$var wire 1 0 rst $end
$var parameter 32 1 div_value $end
$var reg 1 + clk_out $end
$var reg 4 2 count [3:0] $end
$upscope $end
$scope module u2 $end
$var wire 10 3 data_in [9:0] $end
$var wire 3 4 shift_amt [2:0] $end
$var reg 10 5 data_out [9:0] $end
$upscope $end
$scope module u3 $end
$var wire 1 $ clk $end
$var wire 1 % rst $end
$var parameter 32 6 WIDTH $end
$var reg 10 7 rnd [9:0] $end
$upscope $end
$scope module u4 $end
$var wire 10 8 data_in [9:0] $end
$var wire 1 ) parity $end
$upscope $end
$upscope $end
$upscope $end
$enddefinitions $end
$comment Show the parameter values. $end
$dumpall
b1010 6
b100 1
$end
#0
$dumpvars
bx 8
bx 7
bx 5
bx 4
bx 3
b0 2
z0
b0xxxxxxxxxx /
bx .
bx -
bx ,
0+
bx *
x)
bx (
b0 '
b1111 &
0%
0$
b0 #
b1111 "
bx !
$end
#5000
b0 4
b1111 (
b1111 5
b0 /
b1 2
b0 -
0)
b1111 ,
b1111 3
b1111 8
b0xxxxxxxxxx !
b0xxxxxxxxxx .
1$
#10000
0$
#15000
b10 2
b0 !
b0 .
1$
#20000
b1111111111 *
b1111111111 7
0$
1%
#25000
b0 (
b0 5
b11 2
b0 ,
b0 3
b0 8
1$
#30000
0$
#35000
b1 /
1+
b0 2
1$
#40000
0$
0%
#45000
b1111 (
b1111 5
b1 2
b1111111110 *
b1111111110 7
b1111 ,
b1111 3
b1111 8
b1 !
b1 .
1$
#50000
0$
b1100 #
b1100 '
#55000
b11110000 (
b11110000 5
b100 4
b10 2
b1111111100 *
b1111111100 7
b1100 -
1$
#60000
0$
#65000
b11 2
b1111111000 *
b1111111000 7
1$
#70000
0$
#75000
b0 /
0+
b0 2
b1111110000 *
b1111110000 7
1$
#80000
0$
#85000
b1 2
b1111100000 *
b1111100000 7
b0 !
b0 .
1$
#90000
0$
#95000
b10 2
b1111000000 *
b1111000000 7
1$
#100000
0$
#105000
b11 2
b1110000000 *
b1110000000 7
1$
#110000
0$
#115000
b1 /
1+
b0 2
b1100000001 *
b1100000001 7
1$
#120000
0$
#125000
b1 2
b1000000011 *
b1000000011 7
b1 !
b1 .
1$
#130000
0$
#135000
b10 2
b111 *
b111 7
1$
#140000
0$
#145000
b11 2
b1110 *
b1110 7
1$
#150000
0$
#155000
b0 /
0+
b0 2
b11100 *
b11100 7
1$
#160000
0$
#165000
b1 2
b111000 *
b111000 7
b0 !
b0 .
1$
#170000
0$
#175000
b10 2
b1110000 *
b1110000 7
1$
#180000
0$
#185000
b11 2
b11100001 *
b11100001 7
1$
#190000
0$
#195000
b1 /
1+
b0 2
b111000011 *
b111000011 7
1$
#200000
0$
#205000
b1 2
b1110000111 *
b1110000111 7
b1 !
b1 .
1$
#210000
0$
#215000
b10 2
b1100001111 *
b1100001111 7
1$
#220000
0$
#225000
b11 2
b1000011111 *
b1000011111 7
1$
#230000
0$
#235000
b0 /
0+
b0 2
b111111 *
b111111 7
1$
#240000
0$
#245000
b1 2
b1111110 *
b1111110 7
b0 !
b0 .
1$
#250000
0$
#255000
b10 2
b11111101 *
b11111101 7
1$
#260000
0$
#265000
b11 2
b111111011 *
b111111011 7
1$
#270000
0$
#275000
b1 /
1+
b0 2
b1111110111 *
b1111110111 7
1$
#280000
0$
#285000
b1 2
b1111101110 *
b1111101110 7
b1 !
b1 .
1$
#290000
0$
#295000
b10 2
b1111011100 *
b1111011100 7
1$
#300000
0$
#305000
b11 2
b1110111000 *
b1110111000 7
1$
#310000
0$
#315000
b0 /
0+
b0 2
b1101110001 *
b1101110001 7
1$
#320000
0$
#325000
b1 2
b1011100010 *
b1011100010 7
b0 !
b0 .
1$
#330000
0$
#335000
b10 2
b111000100 *
b111000100 7
1$
#340000
0$
#345000
b11 2
b1110001001 *
b1110001001 7
1$
#350000
0$
#355000
b1 /
1+
b0 2
b1100010011 *
b1100010011 7
1$
#360000
0$
#365000
b1 2
b1000100111 *
b1000100111 7
b1 !
b1 .
1$
#370000
0$
#375000
b10 2
b1001111 *
b1001111 7
1$
#380000
0$
#385000
b11 2
b10011111 *
b10011111 7
1$
#390000
0$
#395000
b0 /
0+
b0 2
b100111110 *
b100111110 7
1$
#400000
0$
#405000
b1 2
b1001111100 *
b1001111100 7
b0 !
b0 .
1$
#410000
0$
#415000
b10 2
b11111000 *
b11111000 7
1$
#420000
0$
#425000
b11 2
b111110001 *
b111110001 7
1$
#430000
0$
#435000
b1 /
1+
b0 2
b1111100011 *
b1111100011 7
1$
#440000
0$
#445000
b1 2
b1111000110 *
b1111000110 7
b1 !
b1 .
1$
#450000
0$
#455000
b10 2
b1110001100 *
b1110001100 7
1$
#460000
0$
#465000
b11 2
b1100011001 *
b1100011001 7
1$
#470000
0$
#475000
b0 /
0+
b0 2
b1000110011 *
b1000110011 7
1$
#480000
0$
#485000
b1 2
b1100111 *
b1100111 7
b0 !
b0 .
1$
#490000
0$
#495000
b10 2
b11001111 *
b11001111 7
1$
